setup.py
vutr/__init__.py
vutr/__main__.py
vutr/commands.py
vutr/core.py
vutr.egg-info/PKG-INFO
vutr.egg-info/SOURCES.txt
vutr.egg-info/dependency_links.txt
vutr.egg-info/entry_points.txt
vutr.egg-info/requires.txt
vutr.egg-info/top_level.txt