Metadata-Version: 1.0
Name: vutr
Version: 0.2.1
Summary: CVE Tracker
Home-page: UNKNOWN
Author: UNKNOWN
Author-email: asciimoo@gmail.com
License: AGPLv3
Platform: UNKNOWN
